{"title":"LeetCode 190 and 191","slug":"leetcode-190-and-191","date":"2017-11-20T09:44:49.785Z","updated":"2017-12-11T14:12:45.774Z","comments":true,"excerpt":"<p>没有什么问题是暴力破解不能解决的。 –鲁迅","content":"<p>没有什么问题是暴力破解不能解决的。 –鲁迅<a id=\"more\"></a>  </p>\n<p><a href=\"https://leetcode.com/problems/reverse-bits/description/\" target=\"_blank\" rel=\"external\">Reverse Bits</a><br><a href=\"https://leetcode.com/problems/number-of-1-bits/description/\" target=\"_blank\" rel=\"external\">Number of 1 Bits</a></p>\n<h2 id=\"先说第一道\"><a href=\"#先说第一道\" class=\"headerlink\" title=\"先说第一道\"></a>先说第一道</h2><p>Reverse bits of a given 32 bits unsigned integer.</p>\n<p>For example, given input 43261596 (represented in binary as 00000010100101000001111010011100), return 964176192 (represented in binary as 00111001011110000010100101000000).</p>\n<h2 id=\"题目大意\"><a href=\"#题目大意\" class=\"headerlink\" title=\"题目大意\"></a>题目大意</h2><p>求32位无符号整型的二进制翻转后的结果对应的数</p>\n<h2 id=\"题解\"><a href=\"#题解\" class=\"headerlink\" title=\"题解\"></a>题解</h2><p>emm..我选择<a href=\"https://en.wikipedia.org/wiki/Brute-force_attack\" target=\"_blank\" rel=\"external\">Brute-Force</a><br>用JDK自带函数强行转为二进制再补足32位再翻转再转换。。<br>原本以为会TimeLimited<br>结果居然Accepted了美滋滋 (=ﾟωﾟ)ﾉ<br>代码在<a href=\"https://github.com/Punizione/LeetCode/blob/master/%23190.java\" target=\"_blank\" rel=\"external\">这里</a></p>\n<h2 id=\"第二道\"><a href=\"#第二道\" class=\"headerlink\" title=\"第二道\"></a>第二道</h2><p>Write a function that takes an unsigned integer and returns the number of ’1’ bits it has (also known as the Hamming weight).</p>\n<p>For example, the 32-bit integer ’11’ has binary representation 00000000000000000000000000001011, so the function should return 3.</p>\n<h2 id=\"题目大意-1\"><a href=\"#题目大意-1\" class=\"headerlink\" title=\"题目大意\"></a>题目大意</h2><p>求给定的整型的二进制编码中1的个数</p>\n<h2 id=\"题解-1\"><a href=\"#题解-1\" class=\"headerlink\" title=\"题解\"></a>题解</h2><p>emmm..运气真好竟然连续两道题都能用暴力破解<br>转换后一个循环..<br>代码在<a href=\"https://github.com/Punizione/LeetCode/blob/master/%23191.java\" target=\"_blank\" rel=\"external\">这里</a></p>\n","thumbnail":["http://p0s30qphu.bkt.clouddn.com/17-12-11/30812780.jpg"],"categories":[{"name":"编程","path":"api/categories/编程.json"}],"tags":[{"name":"Java","path":"api/tags/Java.json"},{"name":"算法","path":"api/tags/算法.json"},{"name":"LeetCode","path":"api/tags/LeetCode.json"}]}